opengd77/__init__.py
opengd77/constants.py
opengd77/converters.py
opengd77/csv_models.py
opengd77/models.py
opengd77/py.typed
opengd77-0.3.0.dist-info/METADATA
opengd77-0.3.0.dist-info/WHEEL
opengd77-0.3.0.dist-info/licenses/LICENSE
opengd77-0.3.0.dist-info/RECORD
