Metadata-Version: 2.4
Name: opengd77
Version: 0.3.0
Summary: Python utility to work with the OpenGD77 CPS.
Project-URL: homepage, https://github.com/MicaelJarniac/opengd77
Project-URL: source, https://github.com/MicaelJarniac/opengd77
Project-URL: download, https://pypi.org/project/opengd77/#files
Project-URL: changelog, https://github.com/MicaelJarniac/opengd77/blob/main/docs/CHANGELOG.md
Project-URL: documentation, https://opengd77.readthedocs.io
Project-URL: issues, https://github.com/MicaelJarniac/opengd77/issues
Author-email: Micael Jarniac <micael@jarniac.dev>
License: MIT
License-File: LICENSE
Classifier: Development Status :: 1 - Planning
Classifier: License :: OSI Approved :: MIT License
Classifier: Natural Language :: English
Classifier: Operating System :: OS Independent
Classifier: Programming Language :: Python :: 3
Classifier: Typing :: Typed
Requires-Python: >=3.10
Requires-Dist: attrs>=25.3.0
Requires-Dist: loguru>=0.7.3
